sqdconvert/__init__.py
sqdconvert/__main__.py
sqdconvert/color.py
sqdconvert/config.py
sqdconvert/errors.py
sqdconvert/start.py
sqdconvert/utils.py
sqdconvert-1.2.0.dist-info/LICENSE
sqdconvert-1.2.0.dist-info/METADATA
sqdconvert-1.2.0.dist-info/WHEEL
sqdconvert-1.2.0.dist-info/entry_points.txt
sqdconvert-1.2.0.dist-info/top_level.txt
sqdconvert-1.2.0.dist-info/RECORD
