Metadata-Version: 2.1
Name: sqdconvert
Version: 1.2.0
Summary: convert any audio or video files from one extension to another!
Author: sqdnoises
License: The MIT License (MIT)
Classifier: Programming Language :: Python :: 3
Classifier: License :: OSI Approved :: MIT License
Classifier: Operating System :: OS Independent
Requires-Python: >=3.8
License-File: LICENSE
Requires-Dist: yaspin
Requires-Dist: luddite
